{
  "course": "WDD 130",
  "course_title": "Web Fundamentals",
  "index": 25,
  "lesson": "Week 04",
  "title": "Rafting Site \u2013Update About Us Page",
  "category": "Submit / prove assignment",
  "summary": "W04 Assignment: Rafting Site \u2013 Update About Us Page Use this updated wireframe as a guide to enhance the layout of the about.html page. [Image: Wireframe Design for Rafting Project About Us Page \u2013 Updated] Open the about.html file and the rafting.css files for editing.",
  "url": "https://byui-cse.github.io/wdd130-ww-course/week04/prove-rafting-enhance.html",
  "source_page": "https://byui-cse.github.io/wdd130-ww-course/week04/",
  "status": "ok"
}
